{
    "dashboardMetadata": {
        "name": "{{ .name }}",
        "shared": true,
        "owner": "{{ .owner }}",       
        "dashboardFilter": {
              "managementZone": {
                "id": "{{ .mzId }}",
                "name": "{{ .mzName }}"
            }
        },        
        "tags": ["keptn", "{{ .stage }}", "{{ .project }}", "{{ .service }}"]
    },
"tiles": [
    {
      "name": "Markdown",
      "tileType": "MARKDOWN",
      "configured": true,
      "bounds": {
        "top": 114,
        "left": 0,
        "width": 1102,
        "height": 38
      },
      "tileFilter": {},
      "markdown": "KQG.Total.Pass=90%;KQG.Total.Warning=70%;KQG.Compare.WithScore=pass;KQG.Compare.Results=1;KQG.Compare.Function=avg"
    },
    {
      "name": "Custom chart",
      "tileType": "CUSTOM_CHARTING",
      "configured": true,
      "bounds": {
        "top": 190,
        "left": 0,
        "width": 380,
        "height": 228
      },
      "tileFilter": {},
      "filterConfig": {
        "type": "MIXED",
        "customName": "Response time (P95);sli=svc_rt_p95;pass=<+10%,<600",
        "defaultName": "Custom chart",
        "chartConfig": {
          "legendShown": true,
          "type": "SINGLE_VALUE",
          "series": [
            {
              "metric": "builtin:service.response.time",
              "aggregation": "PERCENTILE",
              "percentile": 95,
              "type": "LINE",
              "entityType": "SERVICE",
              "dimensions": [],
              "sortAscending": false,
              "sortColumn": true,
              "aggregationRate": "TOTAL"
            }
          ],
          "resultMetadata": {}
        },
        "filtersPerEntityType": {}
      }
    },
    {
      "name": "Markdown",
      "tileType": "MARKDOWN",
      "configured": true,
      "bounds": {
        "top": 152,
        "left": 0,
        "width": 380,
        "height": 38
      },
      "tileFilter": {},
      "markdown": "## Service Performance (SLI/SLO)"
    },
    {
      "name": "Markdown",
      "tileType": "MARKDOWN",
      "configured": true,
      "bounds": {
        "top": 152,
        "left": 380,
        "width": 380,
        "height": 38
      },
      "tileFilter": {},
      "markdown": "## Service Errors (SLI/SLO)"
    },
    {
      "name": "Custom chart",
      "tileType": "CUSTOM_CHARTING",
      "configured": true,
      "bounds": {
        "top": 190,
        "left": 380,
        "width": 380,
        "height": 228
      },
      "tileFilter": {},
      "filterConfig": {
        "type": "MIXED",
        "customName": "Failure Rate (Avg);sli=svc_fr;pass=<+10%,<2",
        "defaultName": "Custom chart",
        "chartConfig": {
          "legendShown": true,
          "type": "SINGLE_VALUE",
          "series": [
            {
              "metric": "builtin:service.errors.server.rate",
              "aggregation": "AVG",
              "type": "LINE",
              "entityType": "SERVICE",
              "dimensions": [],
              "sortAscending": false,
              "sortColumn": true,
              "aggregationRate": "TOTAL"
            }
          ],
          "resultMetadata": {}
        },
        "filtersPerEntityType": {}
      }
    },
    {
      "name": "Markdown",
      "tileType": "MARKDOWN",
      "configured": true,
      "bounds": {
        "top": 0,
        "left": 0,
        "width": 1102,
        "height": 114
      },
      "tileFilter": {},
      "markdown": "## SLI/SLO-based Quality Gate Dashboard for {{ .service }} in {{ .stage }} - view results in your [Keptns Bridge](http://https://fvk03152.cloudautomation.live.dynatrace.com/bridge/project/delivery-demo/bridge/project/delivery-demo/{{ .service }})\n\nThis is just a simple dashboard with a single metric. Feel free to extend "
    }
  ]  
}